zenguard/__init__.py
zenguard/zenguard.py
zenguard-0.3.0.dist-info/LICENSE
zenguard-0.3.0.dist-info/METADATA
zenguard-0.3.0.dist-info/WHEEL
zenguard-0.3.0.dist-info/RECORD
